couture_cypher/__init__.py
couture_cypher/coutureCypher.py
Couture_Cypher-0.0.1.dist-info/LICENSE
Couture_Cypher-0.0.1.dist-info/METADATA
Couture_Cypher-0.0.1.dist-info/WHEEL
Couture_Cypher-0.0.1.dist-info/top_level.txt
Couture_Cypher-0.0.1.dist-info/RECORD
